<?xml version="1.0" encoding="UTF-8" ?>
<!-- *************************************************************************************
FILE DESCRIPTION
The file contains the information about all compile points from mapper to be displayed as part of the summary report.
*******************************************************************************************-->
<report_table display_priority="4" name="Compile Points Summary">
<row>
<data>Name</data>
<data>Status</data>
<data>Reason</data>
<data>Real Time</data>
<data>CPU Time</data>
</row>
<row>
<data>
<value>Controler</value>
<report_link name="Report">
<data>C:\VHDL_temp\Digitizer\Digitizer_vhdl\Digitizer\synthesis\Controler\Controler.srr</data>
</report_link>
</data>
<data>Remapped</data>
<data>Interface of Compile Point changed</data>
<data>0h:00m:04s</data>
<data>0h:00m:04s</data>
</row>
<row>
<data>
<value>UART_Protocol_UART_Protocol_0</value>
<report_link name="Report">
<data>C:\VHDL_temp\Digitizer\Digitizer_vhdl\Digitizer\synthesis\UART_Protocol_UART_Protocol_0\UART_Protocol_UART_Protocol_0.srr</data>
</report_link>
</data>
<data>Remapped</data>
<data>Interface of Compile Point changed</data>
<data>0h:00m:04s</data>
<data>0h:00m:04s</data>
</row>
<row>
<data>
<value>UART_Protocol_UART_Protocol_1</value>
<report_link name="Report">
<data>C:\VHDL_temp\Digitizer\Digitizer_vhdl\Digitizer\synthesis\UART_Protocol_UART_Protocol_1\UART_Protocol_UART_Protocol_1.srr</data>
</report_link>
</data>
<data>Remapped</data>
<data>Interface of Compile Point changed</data>
<data>0h:00m:04s</data>
<data>0h:00m:05s</data>
</row>
<row>
<data>
<value>Top</value>
<report_link name="Report">
<data>C:\VHDL_temp\Digitizer\Digitizer_vhdl\Digitizer\synthesis\Top\Top.srr</data>
</report_link>
</data>
<data>Remapped</data>
<data>Interface of a contained Compile Point changed</data>
<data>0h:00m:03s</data>
<data>0h:00m:04s</data>
</row>
<row>
<data>
<value>Communication</value>
<report_link name="Report">
<data>C:\VHDL_temp\Digitizer\Digitizer_vhdl\Digitizer\synthesis\Communication\Communication.srr</data>
</report_link>
</data>
<data>Mapped</data>
<data>No database</data>
<data>0h:00m:05s</data>
<data>0h:00m:05s</data>
</row>
<row>
<data>
<value>Data_Block</value>
<report_link name="Report">
<data>C:\VHDL_temp\Digitizer\Digitizer_vhdl\Digitizer\synthesis\Data_Block\Data_Block.srr</data>
</report_link>
</data>
<data>Remapped</data>
<data>Design changed</data>
<data>0h:00m:26s</data>
<data>0h:00m:26s</data>
</row>
</report_table>
